quilr_litellm_guardrails.py
quilr_litellm_guardrails-0.1.0.dist-info/METADATA
quilr_litellm_guardrails-0.1.0.dist-info/WHEEL
quilr_litellm_guardrails-0.1.0.dist-info/top_level.txt
quilr_litellm_guardrails-0.1.0.dist-info/RECORD
