Metadata-Version: 2.4
Name: quilr-litellm-guardrails
Version: 0.1.0
Summary: Quilr Guardrails Integration for LiteLLM
Author: Quilr
License: MIT
Project-URL: Homepage, https://quilr.ai
Keywords: litellm,guardrails,quilr,llm,ai-safety
Classifier: Development Status :: 4 - Beta
Classifier: Intended Audience :: Developers
Classifier: License :: OSI Approved :: MIT License
Classifier: Programming Language :: Python :: 3
Classifier: Programming Language :: Python :: 3.8
Classifier: Programming Language :: Python :: 3.9
Classifier: Programming Language :: Python :: 3.10
Classifier: Programming Language :: Python :: 3.11
Classifier: Programming Language :: Python :: 3.12
Requires-Python: >=3.8
Requires-Dist: litellm>=1.0.0
